mpbuild/.build.py.swp
mpbuild/__init__.py
mpbuild/__main__.py
mpbuild/board_database.py
mpbuild/build.py
mpbuild/check_images.py
mpbuild/cli.py
mpbuild/completions.py
mpbuild/find_boards.py
mpbuild/interactive.py
mpbuild/list_boards.py
mpbuild/py.typed
mpbuild-0.9.1.dist-info/METADATA
mpbuild-0.9.1.dist-info/WHEEL
mpbuild-0.9.1.dist-info/entry_points.txt
mpbuild-0.9.1.dist-info/licenses/LICENSE
mpbuild-0.9.1.dist-info/RECORD
