Metadata-Version: 2.4
Name: mpbuild
Version: 0.9.1
Summary: Build MicroPython firmware with ease!
Author-email: Matt Trentini <matt.trentini@gmail.com>
License-File: LICENSE
Requires-Python: >=3.12
Requires-Dist: rich>=13.7.1
Requires-Dist: typer>=0.12.3
